government/__init__.py
government/admin.py
government/apps.py
government/conf.py
government/constants.py
government/pagination.py
government/urls.py
government/admin/__init__.py
government/admin/body.py
government/admin/jurisdiction.py
government/admin/office.py
government/admin/party.py
government/management/__init__.py
government/management/commands/__init__.py
government/management/commands/bootstrap_fed.py
government/management/commands/bootstrap_government.py
government/management/commands/bootstrap_jurisdictions.py
government/management/commands/bootstrap_offices.py
government/management/commands/bootstrap_parties.py
government/migrations/0001_initial.py
government/migrations/0002_auto_20180115_1741.py
government/migrations/0003_office_senate_class.py
government/migrations/__init__.py
government/models/__init__.py
government/models/body.py
government/models/jurisdiction.py
government/models/office.py
government/models/party.py
government/serializers/__init__.py
government/serializers/body.py
government/serializers/jurisdiction.py
government/serializers/office.py
government/serializers/party.py
government/utils/__init__.py
government/utils/importers.py
government/viewsets/__init__.py
government/viewsets/base.py
government/viewsets/body.py
government/viewsets/jurisdiction.py
government/viewsets/office.py
government/viewsets/party.py
politico_civic_government-0.1.5.dist-info/METADATA
politico_civic_government-0.1.5.dist-info/RECORD
politico_civic_government-0.1.5.dist-info/WHEEL
politico_civic_government-0.1.5.dist-info/top_level.txt
